reduce_print.py
reduce_print-1.1.0.dist-info/LICENSE
reduce_print-1.1.0.dist-info/METADATA
reduce_print-1.1.0.dist-info/WHEEL
reduce_print-1.1.0.dist-info/top_level.txt
reduce_print-1.1.0.dist-info/RECORD
