Metadata-Version: 2.1
Name: reduce-print
Version: 1.1.0
Summary: A intresting printer of nested lists
Home-page: http://www.headfirstlabs.com
Author: GentleSummer
Author-email: heaven.frostsword@gmail.com
License: UNKNOWN
Platform: UNKNOWN
Classifier: Programming Language :: Python :: 3
Classifier: License :: OSI Approved :: MIT License
Classifier: Operating System :: OS Independent
